{"hash":"9c7b33804577cb67f7a3b80e45b9a0bde245beb4","data":{"post":{"title":"年度 · 2021","path":"/life/2021-annual-summary/","date":"July 11, 2022","timeToRead":0,"cjkWordCount":0,"cjkReadTime":0,"tags":[{"id":"年报","title":"年报","path":"/tag/%E5%B9%B4%E6%8A%A5/"},{"id":"2021","title":"2021","path":"/tag/2021/"}],"cate":{"id":"life","title":"life","path":"/category/life/"},"description":"","ogimage":"","published":false,"content":"\n","cover_image":null},"previous":{"title":"过时的 NoneBot2 插件编写心得","path":"/code/outdated-tips-4-nonebot-2/"},"next":{"title":"NoneBot2 插件编写尝试","path":"/code/experiences-4-nonebot-2/"},"metadata":{"siteUrl":"https://blog.monsterx.cn"}},"context":{"previousElement":"622f2eaa9538047fd6f2cbe70c328070","nextElement":"008620d08995035a06780293b90efc74","id":"80fd281d175f651781df97b10a658c15"}}